{"type":"FeatureCollection","metro_system":{"continent":"asia","country":"India","city":"Sachin","osm_networks":["GMRC"],"operator":null,"official_website":null,"official_map":null,"wikidata":null,"line_count":0,"station_count":2},"features":[{"type":"Feature","properties":{"station_id":"n8468073676","station_name":"Bhesan","station_name_local":"Bhesan","network":"GMRC","network_local":null,"operator":"GMRC","city":"Sachin","country":"India","lines":null,"wikidata":null},"geometry":{"type":"Point","coordinates":[72.7690064,21.2197174]}},{"type":"Feature","properties":{"station_id":"n8468073746","station_name":"Althan Gam","station_name_local":"Althan Gam","network":"GMRC","network_local":null,"operator":"GMRC","city":"Sachin","country":"India","lines":null,"wikidata":null},"geometry":{"type":"Point","coordinates":[72.8079385,21.1525979]}}]}