{"type":"FeatureCollection","metro_system":{"continent":"europe","country":"Germany","city":"Bad Wildbad","osm_networks":["Albtal-Verkehrs-Gesellschaft mbH","DB InfraGO AG","Heilbronner Hohenloher Haller Nahverkehr","Heilbronner Hohenloher Haller Nahverkehr;Karlsruher Verkehrsverbund","Karlsruher Verkehrsverbund","Karlsruher Verkehrsverbund;Tarifverbund Ortenau","Karlsruher Verkehrsverbund;Verkehrs-Gemeinschaft Landkreis Freudenstadt","Unknown"],"operator":"AVG","official_website":"https://www.avg.info/index.html","official_map":"https://de.wikipedia.org/wiki/Karlsruher_Verkehrsverbund","wikidata":"Q1733986","line_count":0,"station_count":1,"audit":null},"features":[{"type":"Feature","properties":{"station_id":"n122317982","station_name":"Hauptbahnhof/Willy-Brandt-Platz","station_name_local":"Hauptbahnhof/Willy-Brandt-Platz","network":"Heilbronner Hohenloher Haller Nahverkehr","network_local":"Heilbronner Hohenloher Haller Nahverkehr","operator":"Stadtwerke Heilbronn GmbH","city":"Bad Wildbad","country":"Germany","lines":["S41"],"wikidata":null},"geometry":{"type":"Point","coordinates":[9.2085288,49.1426294]}}]}