{"type":"FeatureCollection","metro_system":{"continent":"europe","country":"Germany","city":"Walzbachtal","osm_networks":["DB InfraGO AG","Karlsruher Verkehrsverbund"],"operator":"Albtal-Verkehrs-Gesellschaft mbH;DB Regio","official_website":null,"official_map":null,"wikidata":null,"line_count":0,"station_count":1,"audit":null},"features":[{"type":"Feature","properties":{"station_id":"n3321341099","station_name":"Karlsruhe-Mühlburg","station_name_local":"Karlsruhe-Mühlburg","network":"DB InfraGO AG","network_local":null,"operator":"DB InfraGO AG","city":"Walzbachtal","country":"Germany","lines":["S52"],"wikidata":"Q15891050"},"geometry":{"type":"Point","coordinates":[8.3511104,49.0145576]}}]}