{"type":"FeatureCollection","metro_system":{"continent":"asia","country":"Japan","city":"Kanazawa","osm_networks":["北陸鉄道株式会社"],"operator":null,"official_website":null,"official_map":null,"wikidata":null,"line_count":0,"station_count":1},"features":[{"type":"Feature","properties":{"station_id":"n7826372778","station_name":"Hokutetsu Kanazawa","station_name_local":"北鉄金沢","network":"北陸鉄道株式会社","network_local":null,"operator":"北陸鉄道株式会社","city":"Kanazawa","country":"Japan","lines":null,"wikidata":"Q1136378"},"geometry":{"type":"Point","coordinates":[136.6494881,36.5782896]}}]}